pookie/__init__.py
pookie/shell.py
pookie-1.0.0.dist-info/LICENSE
pookie-1.0.0.dist-info/METADATA
pookie-1.0.0.dist-info/WHEEL
pookie-1.0.0.dist-info/entry_points.txt
pookie-1.0.0.dist-info/top_level.txt
pookie-1.0.0.dist-info/RECORD
